Metadata-Version: 1.1
Name: KFlask-AppBuilder
Version: 1.0.1
Summary: Simple and rapid application development framework, built on top of Flask. includes detailed security, auto CRUD generation for your models, google charts and much more.
Home-page: https://github.com/dpgaspar/flask-appbuilder/
Author: Daniel Vaz Gaspar
Author-email: danielvazgaspar@gmail.com
License: BSD
Platform: any
Classifier: Development Status :: 5 - Production/Stable
Classifier: Environment :: Web Environment
Classifier: Intended Audience :: Developers
Classifier: License :: OSI Approved :: BSD License
Classifier: Operating System :: OS Independent
Classifier: Programming Language :: Python
Classifier: Topic :: Software Development :: Libraries :: Python Modules
